ts_analytics/__init__.py
ts_analytics-0.1.1.dist-info/METADATA
ts_analytics-0.1.1.dist-info/RECORD
ts_analytics-0.1.1.dist-info/WHEEL
ts_analytics-0.1.1.dist-info/top_level.txt
