Metadata-Version: 2.1
Name: ts-analytics
Version: 0.1.1
Summary: Traffic data analytics
Home-page: https://github.com/pypa/ts_project
Author: Eneliko Mulokozi
Author-email: emulokozi@aol.com
License: UNKNOWN
Platform: UNKNOWN
Classifier: Programming Language :: Python :: 3
Classifier: License :: OSI Approved :: MIT License
Classifier: Operating System :: OS Independent
